mobilealerts/__init__.py
mobilealerts/gateway.py
mobilealerts/proxy.py
mobilealerts/sensor.py
mobilealerts-0.1.13.dist-info/LICENSE
mobilealerts-0.1.13.dist-info/METADATA
mobilealerts-0.1.13.dist-info/WHEEL
mobilealerts-0.1.13.dist-info/RECORD
