Metadata-Version: 2.1
Name: mobilealerts
Version: 0.1.13
Summary: Python classes for MobileAlerts gateway and sensors
Home-page: https://github.com/PlusPlus-ua/python-mobilealerts
License: MIT
Author: PlusPlus-ua
Author-email: alexplas@gmail.com
Requires-Python: >=3.7,<4.0
Classifier: Development Status :: 3 - Alpha
Classifier: Intended Audience :: Developers
Classifier: License :: OSI Approved :: MIT License
Classifier: Operating System :: OS Independent
Classifier: Programming Language :: Python :: 3
Classifier: Programming Language :: Python :: 3.7
Classifier: Programming Language :: Python :: 3.8
Classifier: Programming Language :: Python :: 3.9
Classifier: Programming Language :: Python :: 3.10
Classifier: Programming Language :: Python :: 3.11
Classifier: Programming Language :: Python :: 3
Classifier: Programming Language :: Python :: 3.7
Classifier: Programming Language :: Python :: 3.8
Classifier: Programming Language :: Python :: 3.9
Classifier: Topic :: Software Development :: Libraries :: Python Modules
Requires-Dist: aiohttp (>=3.8,<4.0)
Requires-Dist: importlib_metadata (>=4.5,<7.0) ; python_version < "3.8"
Project-URL: Repository, https://github.com/PlusPlus-ua/python-mobilealerts
